easychain/__init__.py
easychain/blockchain.py
easychain/exception.py
easychain-0.2.1.dist-info/DESCRIPTION.rst
easychain-0.2.1.dist-info/METADATA
easychain-0.2.1.dist-info/RECORD
easychain-0.2.1.dist-info/WHEEL
easychain-0.2.1.dist-info/metadata.json
easychain-0.2.1.dist-info/top_level.txt
