Metadata-Version: 2.0
Name: easychain
Version: 0.2.1
Summary: Simple library to easily export blockchain
Home-page: https://github.com/valder/easychain
Author: valdergallo, davecan
Author-email: valdergallo@gmail.com
License: MIT
Download-URL: https://github.com/valder/easychain/tarball/0.2.1/
Keywords: Blockchain
Platform: any
Classifier: Development Status :: 4 - Beta
Classifier: Operating System :: OS Independent
Classifier: Topic :: Utilities
Classifier: Programming Language :: Python :: 2.7
Classifier: Programming Language :: Python :: 3
Classifier: Programming Language :: Python :: 3.2
Classifier: Programming Language :: Python :: 3.3
Classifier: Programming Language :: Python :: 3.4
Classifier: Programming Language :: Python :: 3.5
Classifier: Programming Language :: Python :: 3.6
